odoo/addons/l10n_th_partner/README.rst
odoo/addons/l10n_th_partner/__init__.py
odoo/addons/l10n_th_partner/__manifest__.py
odoo/addons/l10n_th_partner/i18n/l10n_th_partner.pot
odoo/addons/l10n_th_partner/models/__init__.py
odoo/addons/l10n_th_partner/models/res_partner.py
odoo/addons/l10n_th_partner/readme/CONTRIBUTORS.rst
odoo/addons/l10n_th_partner/readme/DESCRIPTION.rst
odoo/addons/l10n_th_partner/static/description/icon.png
odoo/addons/l10n_th_partner/static/description/index.html
odoo/addons/l10n_th_partner/views/res_partner_view.xml
odoo12_addon_l10n_th_partner-12.0.1.0.0.99.dev7.dist-info/METADATA
odoo12_addon_l10n_th_partner-12.0.1.0.0.99.dev7.dist-info/WHEEL
odoo12_addon_l10n_th_partner-12.0.1.0.0.99.dev7.dist-info/top_level.txt
odoo12_addon_l10n_th_partner-12.0.1.0.0.99.dev7.dist-info/RECORD
